{
  "1": {
    "inputs": {
      "face": [ "2", 0 ],
      "driving_audio": [ "3", 0 ],
      "emo_checkpoint": "emo_v1.pth",
      "emotion_intensity": 1.0
    },
    "class_type": "EMO_AnimateFace",
    "_meta": { "title": "EMO Face Animation" }
  },
  "2": {
    "inputs": {
      "image": "example_face.png",
      "upload": "image"
    },
    "class_type": "LoadImage",
    "_meta": { "title": "Load Face Image" }
  },
  "3": {
    "inputs": {
      "audio_file": "example_audio.wav"
    },
    "class_type": "LoadAudio",
    "_meta": { "title": "Load Driving Audio" }
  },
  "4": {
    "inputs": {
      "frame_rate": 25,
      "loop_count": 0,
      "filename_prefix": "Morpheus_LipSync_EMO",
      "format": "video/h264-mp4",
      "images": [ "1", 0 ]
    },
    "class_type": "VHS_VideoCombine",
    "_meta": { "title": "Save Animated Video" }
  }
}
